hello.py
py_zeval-0.0.1.dist-info/METADATA
py_zeval-0.0.1.dist-info/WHEEL
py_zeval-0.0.1.dist-info/top_level.txt
py_zeval-0.0.1.dist-info/RECORD
